{
  "bookId": "Phlm",
  "cuvVerses": [
    {
      "book": "Phlm",
      "chapter": 1,
      "id": "Phlm.1.1",
      "text": "为基督耶稣被囚的保罗同兄弟提摩太，写信给我们所亲爱的同工腓利门，",
      "verse": 1
    },
    {
      "book": "Phlm",
      "chapter": 1,
      "id": "Phlm.1.2",
      "text": "和妹子亚腓亚，并与我们同当兵的亚基布，以及在你家的教会：",
      "verse": 2
    },
    {
      "book": "Phlm",
      "chapter": 1,
      "id": "Phlm.1.3",
      "text": "愿恩惠、平安从 神我们的父和主耶稣基督归与你们！",
      "verse": 3
    },
    {
      "book": "Phlm",
      "chapter": 1,
      "id": "Phlm.1.4",
      "text": "我祷告的时候提到你，常为你感谢我的 神，",
      "verse": 4
    },
    {
      "book": "Phlm",
      "chapter": 1,
      "id": "Phlm.1.5",
      "text": "因听说你的爱心并你向主耶稣和众圣徒的信心（注：或作“因听说你向主耶稣和众圣徒有爱心、有信 心” ） 。",
      "verse": 5
    },
    {
      "book": "Phlm",
      "chapter": 1,
      "id": "Phlm.1.6",
      "text": "愿你与人所同有的信心显出功效，使人知道你们各样善事都是为基督做的。",
      "verse": 6
    },
    {
      "book": "Phlm",
      "chapter": 1,
      "id": "Phlm.1.7",
      "text": "兄弟啊，我为你的爱心大有快乐，大得安慰，因众圣徒的心从你得了畅快。",
      "verse": 7
    },
    {
      "book": "Phlm",
      "chapter": 1,
      "id": "Phlm.1.8",
      "text": "我虽然靠着基督能放胆吩咐你合宜的事，",
      "verse": 8
    },
    {
      "book": "Phlm",
      "chapter": 1,
      "id": "Phlm.1.9",
      "text": "然而像我这有年纪的保罗，现在又是为基督耶稣被囚的，宁可凭着爱心求你，",
      "verse": 9
    },
    {
      "book": "Phlm",
      "chapter": 1,
      "id": "Phlm.1.10",
      "text": "就是为我在捆锁中所生的儿子阿尼西母（注：此名就是“有益处”的意思）求你。",
      "verse": 10
    },
    {
      "book": "Phlm",
      "chapter": 1,
      "id": "Phlm.1.11",
      "text": "他从前与你没有益处，但如今与你我都有益处。",
      "verse": 11
    },
    {
      "book": "Phlm",
      "chapter": 1,
      "id": "Phlm.1.12",
      "text": "我现在打发他亲自回你那里去，他是我心上的人。",
      "verse": 12
    },
    {
      "book": "Phlm",
      "chapter": 1,
      "id": "Phlm.1.13",
      "text": "我本来有意将他留下，在我为福音所受的捆锁中替你伺候我；",
      "verse": 13
    },
    {
      "book": "Phlm",
      "chapter": 1,
      "id": "Phlm.1.14",
      "text": "但不知道你的意思，我就不愿意这样行，叫你的善行不是出于勉强，乃是出于甘心。",
      "verse": 14
    },
    {
      "book": "Phlm",
      "chapter": 1,
      "id": "Phlm.1.15",
      "text": "他暂时离开你，或者是叫你永远得着他；",
      "verse": 15
    },
    {
      "book": "Phlm",
      "chapter": 1,
      "id": "Phlm.1.16",
      "text": "不再是奴仆，乃是高过奴仆，是亲爱的兄弟。在我实在是如此，何况在你呢！这也不拘是按肉体说， 是按主说。",
      "verse": 16
    },
    {
      "book": "Phlm",
      "chapter": 1,
      "id": "Phlm.1.17",
      "text": "你若以我为同伴，就收纳他，如同收纳我一样。",
      "verse": 17
    },
    {
      "book": "Phlm",
      "chapter": 1,
      "id": "Phlm.1.18",
      "text": "他若亏负你，或欠你什么，都归在我的账上，",
      "verse": 18
    },
    {
      "book": "Phlm",
      "chapter": 1,
      "id": "Phlm.1.19",
      "text": "我必偿还。这是我保罗亲笔写的。我并不用对你说，连你自己也是亏欠于我。",
      "verse": 19
    },
    {
      "book": "Phlm",
      "chapter": 1,
      "id": "Phlm.1.20",
      "text": "兄弟啊，望你使我在主里因你得快乐（注：或作“益处” ） ，并望你使我的心在基督里得畅快。",
      "verse": 20
    },
    {
      "book": "Phlm",
      "chapter": 1,
      "id": "Phlm.1.21",
      "text": "我写信给你，深信你必顺服，知道你所要行的，必过于我所说的。",
      "verse": 21
    },
    {
      "book": "Phlm",
      "chapter": 1,
      "id": "Phlm.1.22",
      "text": "此外，你还要给我预备住处，因为我盼望藉着你们的祷告，必蒙恩到你们那里去。",
      "verse": 22
    },
    {
      "book": "Phlm",
      "chapter": 1,
      "id": "Phlm.1.23",
      "text": "为基督耶稣与我同坐监的以巴弗问你安。",
      "verse": 23
    },
    {
      "book": "Phlm",
      "chapter": 1,
      "id": "Phlm.1.24",
      "text": "与我同工的马可、亚里达古、底马、路加也都问你安。",
      "verse": 24
    },
    {
      "book": "Phlm",
      "chapter": 1,
      "id": "Phlm.1.25",
      "text": "愿我们主耶稣基督的恩常在你的心里。阿们。",
      "verse": 25
    }
  ],
  "kjvVerses": [
    {
      "book": "Phlm",
      "chapter": 1,
      "id": "Phlm.1.1",
      "text": "Paul, a prisoner of Jesus Christ, and Timothy our brother, unto Philemon our dearly beloved, and fellowlabourer,",
      "verse": 1
    },
    {
      "book": "Phlm",
      "chapter": 1,
      "id": "Phlm.1.2",
      "text": "And to [our] beloved Apphia, and Archippus our fellowsoldier, and to the church in thy house:",
      "verse": 2
    },
    {
      "book": "Phlm",
      "chapter": 1,
      "id": "Phlm.1.3",
      "text": "Grace to you, and peace, from God our Father and the Lord Jesus Christ.",
      "verse": 3
    },
    {
      "book": "Phlm",
      "chapter": 1,
      "id": "Phlm.1.4",
      "text": "I thank my God, making mention of thee always in my prayers,",
      "verse": 4
    },
    {
      "book": "Phlm",
      "chapter": 1,
      "id": "Phlm.1.5",
      "text": "Hearing of thy love and faith, which thou hast toward the Lord Jesus, and toward all saints;",
      "verse": 5
    },
    {
      "book": "Phlm",
      "chapter": 1,
      "id": "Phlm.1.6",
      "text": "That the communication of thy faith may become effectual by the acknowledging of every good thing which is in you in Christ Jesus.",
      "verse": 6
    },
    {
      "book": "Phlm",
      "chapter": 1,
      "id": "Phlm.1.7",
      "text": "For we have great joy and consolation in thy love, because the bowels of the saints are refreshed by thee, brother.",
      "verse": 7
    },
    {
      "book": "Phlm",
      "chapter": 1,
      "id": "Phlm.1.8",
      "text": "Wherefore, though I might be much bold in Christ to enjoin thee that which is convenient,",
      "verse": 8
    },
    {
      "book": "Phlm",
      "chapter": 1,
      "id": "Phlm.1.9",
      "text": "Yet for love’s sake I rather beseech [thee,] being such an one as Paul the aged, and now also a prisoner of Jesus Christ.",
      "verse": 9
    },
    {
      "book": "Phlm",
      "chapter": 1,
      "id": "Phlm.1.10",
      "text": "I beseech thee for my son Onesimus, whom I have begotten in my bonds:",
      "verse": 10
    },
    {
      "book": "Phlm",
      "chapter": 1,
      "id": "Phlm.1.11",
      "text": "Which in time past was to thee unprofitable, but now profitable to thee and to me:",
      "verse": 11
    },
    {
      "book": "Phlm",
      "chapter": 1,
      "id": "Phlm.1.12",
      "text": "Whom I have sent again: thou therefore receive him, that is, mine own bowels:",
      "verse": 12
    },
    {
      "book": "Phlm",
      "chapter": 1,
      "id": "Phlm.1.13",
      "text": "Whom I would have retained with me, that in thy stead he might have ministered unto me in the bonds of the gospel:",
      "verse": 13
    },
    {
      "book": "Phlm",
      "chapter": 1,
      "id": "Phlm.1.14",
      "text": "But without thy mind would I do nothing; that thy benefit should not be as it were of necessity, but willingly.",
      "verse": 14
    },
    {
      "book": "Phlm",
      "chapter": 1,
      "id": "Phlm.1.15",
      "text": "For perhaps he therefore departed for a season, that thou shouldest receive him for ever;",
      "verse": 15
    },
    {
      "book": "Phlm",
      "chapter": 1,
      "id": "Phlm.1.16",
      "text": "Not now as a servant, but above a servant, a brother beloved, specially to me, but how much more unto thee, both in the flesh, and in the Lord?",
      "verse": 16
    },
    {
      "book": "Phlm",
      "chapter": 1,
      "id": "Phlm.1.17",
      "text": "If thou count me therefore a partner, receive him as myself.",
      "verse": 17
    },
    {
      "book": "Phlm",
      "chapter": 1,
      "id": "Phlm.1.18",
      "text": "If he hath wronged thee, or oweth [thee] ought, put that on mine account;",
      "verse": 18
    },
    {
      "book": "Phlm",
      "chapter": 1,
      "id": "Phlm.1.19",
      "text": "I Paul have written [it] with mine own hand, I will repay [it:] albeit I do not say to thee how thou owest unto me even thine own self besides.",
      "verse": 19
    },
    {
      "book": "Phlm",
      "chapter": 1,
      "id": "Phlm.1.20",
      "text": "Yea, brother, let me have joy of thee in the Lord: refresh my bowels in the Lord.",
      "verse": 20
    },
    {
      "book": "Phlm",
      "chapter": 1,
      "id": "Phlm.1.21",
      "text": "Having confidence in thy obedience I wrote unto thee, knowing that thou wilt also do more than I say.",
      "verse": 21
    },
    {
      "book": "Phlm",
      "chapter": 1,
      "id": "Phlm.1.22",
      "text": "But withal prepare me also a lodging: for I trust that through your prayers I shall be given unto you.",
      "verse": 22
    },
    {
      "book": "Phlm",
      "chapter": 1,
      "id": "Phlm.1.23",
      "text": "There salute thee Epaphras, my fellowprisoner in Christ Jesus;",
      "verse": 23
    },
    {
      "book": "Phlm",
      "chapter": 1,
      "id": "Phlm.1.24",
      "text": "Marcus, Aristarchus, Demas, Lucas, my fellowlabourers.",
      "verse": 24
    },
    {
      "book": "Phlm",
      "chapter": 1,
      "id": "Phlm.1.25",
      "text": "The grace of our Lord Jesus Christ [be] with your spirit. Amen.",
      "verse": 25
    }
  ],
  "schemaVersion": 1,
  "textCards": [
    {
      "body": "没有益处……有益处（希腊原文achrestos..euchrestos）.保罗在这里使用双关语描述阿尼西母信主前后的转变。阿尼西母偷了腓利门的东西后逃走，他对腓利门是\"没处\"的人：但后来他悔改，并降服于基督，成为对腓利门都\"有益处\"的人。这样的转变凸显了福音改变人的大能。",
      "debugMeta": {
        "coverageRanges": [
          {
            "end": "Phlm.1.11",
            "start": "Phlm.1.11"
          }
        ],
        "page": 3,
        "primaryAnchor": "Phlm.1.11",
        "sourceLabel": "圣经研修本 57_腓利门书【codex-v3】"
      },
      "id": "study-bible-phlm-11-p003-n014",
      "primaryAnchor": "Phlm.1.11",
      "searchText": "腓利门书 11 研修本注释\n没有益处……有益处（希腊原文achrestos..euchrestos）.保罗在这里使用双关语描述阿尼西母信主前后的转变。阿尼西母偷了腓利门的东西后逃走，他对腓利门是\"没处\"的人：但后来他悔改，并降服于基督，成为对腓利门都\"有益处\"的人。…\n没有益处……有益处（希腊原文achrestos..euchrestos）.保罗在这里使用双关语描述阿尼西母信主前后的转变。阿尼西母偷了腓利门的东西后逃走，他对腓利门是\"没处\"的人：但后来他悔改，并降服于基督，成为对腓利门都\"有益处\"的人。这样的转变凸显了福音改变人的大能。\n11\n圣经研修本 57_腓利门书【codex-v3】",
      "source": "圣经研修本 57_腓利门书【codex-v3】",
      "summary": "没有益处……有益处（希腊原文achrestos..euchrestos）.保罗在这里使用双关语描述阿尼西母信主前后的转变。阿尼西母偷了腓利门的东西后逃走，他对腓利门是\"没处\"的人：但后来他悔改，并降服于基督，成为对腓利门都\"有益处\"的人。…",
      "title": "腓利门书 11 研修本注释",
      "type": "commentary",
      "verses": [
        "Phlm.1.11"
      ]
    },
    {
      "body": "我心上的人（《和修》\"我心肝\"，这里的\"心\"希腊原文是splagchna（直译：内脏，尤指胃和肠），而不是常见的kardia。Splagchna这个词表达亲密的感情和深厚的爱（参7、20节：腓2:1：西3:12）。保罗不是以置身事外的仲裁者身份，而是作为一个与阿尼西母建立了深厚感情的人来处理这件事。",
      "debugMeta": {
        "coverageRanges": [
          {
            "end": "Phlm.1.12",
            "start": "Phlm.1.12"
          }
        ],
        "page": 4,
        "primaryAnchor": "Phlm.1.12",
        "sourceLabel": "圣经研修本 57_腓利门书【codex-v3】"
      },
      "id": "study-bible-phlm-12-p004-n015",
      "primaryAnchor": "Phlm.1.12",
      "searchText": "腓利门书 12 研修本注释\n我心上的人（《和修》\"我心肝\"，这里的\"心\"希腊原文是splagchna（直译：内脏，尤指胃和肠），而不是常见的kardia。Splagchna这个词表达亲密的感情和深厚的爱（参7、20节：腓2:1：西3:12）。保罗不是以置身事外的仲裁…\n我心上的人（《和修》\"我心肝\"，这里的\"心\"希腊原文是splagchna（直译：内脏，尤指胃和肠），而不是常见的kardia。Splagchna这个词表达亲密的感情和深厚的爱（参7、20节：腓2:1：西3:12）。保罗不是以置身事外的仲裁者身份，而是作为一个与阿尼西母建立了深厚感情的人来处理这件事。\n12\n圣经研修本 57_腓利门书【codex-v3】",
      "source": "圣经研修本 57_腓利门书【codex-v3】",
      "summary": "我心上的人（《和修》\"我心肝\"，这里的\"心\"希腊原文是splagchna（直译：内脏，尤指胃和肠），而不是常见的kardia。Splagchna这个词表达亲密的感情和深厚的爱（参7、20节：腓2:1：西3:12）。保罗不是以置身事外的仲裁…",
      "title": "腓利门书 12 研修本注释",
      "type": "commentary",
      "verses": [
        "Phlm.1.12"
      ]
    },
    {
      "body": "他 离开你，希腊原文的动词是被动语态，但没有指明是谁使阿尼西母离开。我们最好把这个被动语态理解为\"出于上帝的\"或\"属天的带领\".即上帝主导了这件事情。这使人想起《旧约》中的约瑟被哥哥们出卖，长期寄居埃及：后来与他们相认时，约瑟说：\"差我到这里来的不是你们，乃是上帝（创45:8）。",
      "debugMeta": {
        "coverageRanges": [
          {
            "end": "Phlm.1.15",
            "start": "Phlm.1.15"
          }
        ],
        "page": 4,
        "primaryAnchor": "Phlm.1.15",
        "sourceLabel": "圣经研修本 57_腓利门书【codex-v3】"
      },
      "id": "study-bible-phlm-15-p004-n017",
      "primaryAnchor": "Phlm.1.15",
      "searchText": "腓利门书 15 研修本注释\n他 离开你，希腊原文的动词是被动语态，但没有指明是谁使阿尼西母离开。我们最好把这个被动语态理解为\"出于上帝的\"或\"属天的带领\".即上帝主导了这件事情。这使人想起《旧约》中的约瑟被哥哥们出卖，长期寄居埃及：后来与他们相认时，约瑟说：\"差我到…\n他 离开你，希腊原文的动词是被动语态，但没有指明是谁使阿尼西母离开。我们最好把这个被动语态理解为\"出于上帝的\"或\"属天的带领\".即上帝主导了这件事情。这使人想起《旧约》中的约瑟被哥哥们出卖，长期寄居埃及：后来与他们相认时，约瑟说：\"差我到这里来的不是你们，乃是上帝（创45:8）。\n15\n圣经研修本 57_腓利门书【codex-v3】",
      "source": "圣经研修本 57_腓利门书【codex-v3】",
      "summary": "他 离开你，希腊原文的动词是被动语态，但没有指明是谁使阿尼西母离开。我们最好把这个被动语态理解为\"出于上帝的\"或\"属天的带领\".即上帝主导了这件事情。这使人想起《旧约》中的约瑟被哥哥们出卖，长期寄居埃及：后来与他们相认时，约瑟说：\"差我到…",
      "title": "腓利门书 15 研修本注释",
      "type": "commentary",
      "verses": [
        "Phlm.1.15"
      ]
    },
    {
      "body": "不再是奴仆（原文直译：不再好像奴仆-样），保罗大可更明确地说\"他不再是奴仆\"，清楚表明他期望阿尼西母得着自由。关于希腊原文doulos，见《读者指南》。\"好像……一样\"这个词（希腊原文hos：《和》没有译出）暗示，保罗让腓利门自己去思考该怎样做，然后做出正确的选择.而不是由保罗直接吩咐他去做。但显然保罗期望他们两人之间的关系会有彻底的改变，因为如今阿尼西母已经是腓利门亲爱的兄弟。",
      "debugMeta": {
        "coverageRanges": [
          {
            "end": "Phlm.1.16",
            "start": "Phlm.1.16"
          }
        ],
        "page": 4,
        "primaryAnchor": "Phlm.1.16",
        "sourceLabel": "圣经研修本 57_腓利门书【codex-v3】"
      },
      "id": "study-bible-phlm-16-p004-n018",
      "primaryAnchor": "Phlm.1.16",
      "searchText": "腓利门书 16 研修本注释：不再是奴仆（原文直译\n不再是奴仆（原文直译：不再好像奴仆-样），保罗大可更明确地说\"他不再是奴仆\"，清楚表明他期望阿尼西母得着自由。关于希腊原文doulos，见《读者指南》。\"好像……一样\"这个词（希腊原文hos：《和》没有译出）暗示，保罗让腓利门自己去思考该…\n不再是奴仆（原文直译：不再好像奴仆-样），保罗大可更明确地说\"他不再是奴仆\"，清楚表明他期望阿尼西母得着自由。关于希腊原文doulos，见《读者指南》。\"好像……一样\"这个词（希腊原文hos：《和》没有译出）暗示，保罗让腓利门自己去思考该怎样做，然后做出正确的选择.而不是由保罗直接吩咐他去做。但显然保罗期望他们两人之间的关系会有彻底的改变，因为如今阿尼西母已经是腓利门亲爱的兄弟。\n16\n圣经研修本 57_腓利门书【codex-v3】",
      "source": "圣经研修本 57_腓利门书【codex-v3】",
      "summary": "不再是奴仆（原文直译：不再好像奴仆-样），保罗大可更明确地说\"他不再是奴仆\"，清楚表明他期望阿尼西母得着自由。关于希腊原文doulos，见《读者指南》。\"好像……一样\"这个词（希腊原文hos：《和》没有译出）暗示，保罗让腓利门自己去思考该…",
      "title": "腓利门书 16 研修本注释：不再是奴仆（原文直译",
      "type": "commentary",
      "verses": [
        "Phlm.1.16"
      ]
    },
    {
      "body": "同伴（希腊原文koinonos）与第6节\"与人所同有的\"（希腊原文koinonia）词根相同。腓利门的善良这时应当体现在他与阿尼西母的新关系上。上帝已经为基督的缘故接纳了他的百姓.因此他们也当彼此接纳（见罗5:6-11：林后5:16-21；见林后2:10注）。",
      "debugMeta": {
        "coverageRanges": [
          {
            "end": "Phlm.1.17",
            "start": "Phlm.1.17"
          }
        ],
        "page": 4,
        "primaryAnchor": "Phlm.1.17",
        "sourceLabel": "圣经研修本 57_腓利门书【codex-v3】"
      },
      "id": "study-bible-phlm-17-p004-n019",
      "primaryAnchor": "Phlm.1.17",
      "searchText": "腓利门书 17 研修本注释\n同伴（希腊原文koinonos）与第6节\"与人所同有的\"（希腊原文koinonia）词根相同。腓利门的善良这时应当体现在他与阿尼西母的新关系上。上帝已经为基督的缘故接纳了他的百姓.因此他们也当彼此接纳（见罗5:6-11：林后5:16-21…\n同伴（希腊原文koinonos）与第6节\"与人所同有的\"（希腊原文koinonia）词根相同。腓利门的善良这时应当体现在他与阿尼西母的新关系上。上帝已经为基督的缘故接纳了他的百姓.因此他们也当彼此接纳（见罗5:6-11：林后5:16-21；见林后2:10注）。\n17\n圣经研修本 57_腓利门书【codex-v3】",
      "source": "圣经研修本 57_腓利门书【codex-v3】",
      "summary": "同伴（希腊原文koinonos）与第6节\"与人所同有的\"（希腊原文koinonia）词根相同。腓利门的善良这时应当体现在他与阿尼西母的新关系上。上帝已经为基督的缘故接纳了他的百姓.因此他们也当彼此接纳（见罗5:6-11：林后5:16-21…",
      "title": "腓利门书 17 研修本注释",
      "type": "commentary",
      "verses": [
        "Phlm.1.17"
      ]
    },
    {
      "body": "在第7节，保罗说他大有快乐，因为\"众圣徒的心从你（腓利门）得了畅快\"：在12节，保罗说\"我现在发…我心上的人。在这里，保罗第三次使用希腊原文splagchna（\"心），吩咐腓利门要使我的心在基督里得畅快。上帝在腓利门生命中所做的工作，现在要藉着他和阿尼西母的关系彰显出来。",
      "debugMeta": {
        "coverageRanges": [
          {
            "end": "Phlm.1.20",
            "start": "Phlm.1.20"
          }
        ],
        "page": 4,
        "primaryAnchor": "Phlm.1.20",
        "sourceLabel": "圣经研修本 57_腓利门书【codex-v3】"
      },
      "id": "study-bible-phlm-20-p004-n021",
      "primaryAnchor": "Phlm.1.20",
      "searchText": "腓利门书 20 研修本注释\n在第7节，保罗说他大有快乐，因为\"众圣徒的心从你（腓利门）得了畅快\"：在12节，保罗说\"我现在发…我心上的人。在这里，保罗第三次使用希腊原文splagchna（\"心），吩咐腓利门要使我的心在基督里得畅快。上帝在腓利门生命中所做的工作，现在…\n在第7节，保罗说他大有快乐，因为\"众圣徒的心从你（腓利门）得了畅快\"：在12节，保罗说\"我现在发…我心上的人。在这里，保罗第三次使用希腊原文splagchna（\"心），吩咐腓利门要使我的心在基督里得畅快。上帝在腓利门生命中所做的工作，现在要藉着他和阿尼西母的关系彰显出来。\n20\n圣经研修本 57_腓利门书【codex-v3】",
      "source": "圣经研修本 57_腓利门书【codex-v3】",
      "summary": "在第7节，保罗说他大有快乐，因为\"众圣徒的心从你（腓利门）得了畅快\"：在12节，保罗说\"我现在发…我心上的人。在这里，保罗第三次使用希腊原文splagchna（\"心），吩咐腓利门要使我的心在基督里得畅快。上帝在腓利门生命中所做的工作，现在…",
      "title": "腓利门书 20 研修本注释",
      "type": "commentary",
      "verses": [
        "Phlm.1.20"
      ]
    },
    {
      "body": "有些人认为，你所要行的必过于我所说的，这是指让阿尼西母恢复自由。有些人认为，保罗在这里是暗示腓利门要差遺阿尼西母回去伺候他（参13-14节）。保罗可能有意让腓利门自己决定怎样做是最好的，所以不给他任何具体的指示。",
      "debugMeta": {
        "coverageRanges": [
          {
            "end": "Phlm.1.21",
            "start": "Phlm.1.21"
          }
        ],
        "page": 4,
        "primaryAnchor": "Phlm.1.21",
        "sourceLabel": "圣经研修本 57_腓利门书【codex-v3】"
      },
      "id": "study-bible-phlm-21-p004-n023",
      "primaryAnchor": "Phlm.1.21",
      "searchText": "腓利门书 21 研修本注释\n有些人认为，你所要行的必过于我所说的，这是指让阿尼西母恢复自由。有些人认为，保罗在这里是暗示腓利门要差遺阿尼西母回去伺候他（参13-14节）。保罗可能有意让腓利门自己决定怎样做是最好的，所以不给他任何具体的指示。\n有些人认为，你所要行的必过于我所说的，这是指让阿尼西母恢复自由。有些人认为，保罗在这里是暗示腓利门要差遺阿尼西母回去伺候他（参13-14节）。保罗可能有意让腓利门自己决定怎样做是最好的，所以不给他任何具体的指示。\n21\n圣经研修本 57_腓利门书【codex-v3】",
      "source": "圣经研修本 57_腓利门书【codex-v3】",
      "summary": "有些人认为，你所要行的必过于我所说的，这是指让阿尼西母恢复自由。有些人认为，保罗在这里是暗示腓利门要差遺阿尼西母回去伺候他（参13-14节）。保罗可能有意让腓利门自己决定怎样做是最好的，所以不给他任何具体的指示。",
      "title": "腓利门书 21 研修本注释",
      "type": "commentary",
      "verses": [
        "Phlm.1.21"
      ]
    },
    {
      "body": "给我预备住处，保罗盼望从狱中获释，能有机会去歌罗西。这是否表示保罗此时已放弃（或至少推延）之前要去西班牙的计划，我们无法确知。",
      "debugMeta": {
        "coverageRanges": [
          {
            "end": "Phlm.1.22",
            "start": "Phlm.1.22"
          }
        ],
        "page": 4,
        "primaryAnchor": "Phlm.1.22",
        "sourceLabel": "圣经研修本 57_腓利门书【codex-v3】"
      },
      "id": "study-bible-phlm-22-p004-n024",
      "primaryAnchor": "Phlm.1.22",
      "searchText": "腓利门书 22 研修本注释\n给我预备住处，保罗盼望从狱中获释，能有机会去歌罗西。这是否表示保罗此时已放弃（或至少推延）之前要去西班牙的计划，我们无法确知。\n给我预备住处，保罗盼望从狱中获释，能有机会去歌罗西。这是否表示保罗此时已放弃（或至少推延）之前要去西班牙的计划，我们无法确知。\n22\n圣经研修本 57_腓利门书【codex-v3】",
      "source": "圣经研修本 57_腓利门书【codex-v3】",
      "summary": "给我预备住处，保罗盼望从狱中获释，能有机会去歌罗西。这是否表示保罗此时已放弃（或至少推延）之前要去西班牙的计划，我们无法确知。",
      "title": "腓利门书 22 研修本注释",
      "type": "commentary",
      "verses": [
        "Phlm.1.22"
      ]
    },
    {
      "body": "与腓利门一样，以巴弗是歌罗西人。他为上帝所用，在歌罗西建立了教会（西1:7，4:12）。这时以巴弗和保罗一起在罗马，为基督耶稣……同坐监。至于以巴弗为何被捕，我们不得而知。",
      "debugMeta": {
        "coverageRanges": [
          {
            "end": "Phlm.1.23",
            "start": "Phlm.1.23"
          }
        ],
        "page": 4,
        "primaryAnchor": "Phlm.1.23",
        "sourceLabel": "圣经研修本 57_腓利门书【codex-v3】"
      },
      "id": "study-bible-phlm-23-p004-n025",
      "primaryAnchor": "Phlm.1.23",
      "searchText": "腓利门书 23 研修本注释：与腓利门一样，以巴弗是歌罗西人\n与腓利门一样，以巴弗是歌罗西人。他为上帝所用，在歌罗西建立了教会（西1:7，4:12）。这时以巴弗和保罗一起在罗马，为基督耶稣……同坐监。至于以巴弗为何被捕，我们不得而知。\n与腓利门一样，以巴弗是歌罗西人。他为上帝所用，在歌罗西建立了教会（西1:7，4:12）。这时以巴弗和保罗一起在罗马，为基督耶稣……同坐监。至于以巴弗为何被捕，我们不得而知。\n23\n圣经研修本 57_腓利门书【codex-v3】",
      "source": "圣经研修本 57_腓利门书【codex-v3】",
      "summary": "与腓利门一样，以巴弗是歌罗西人。他为上帝所用，在歌罗西建立了教会（西1:7，4:12）。这时以巴弗和保罗一起在罗马，为基督耶稣……同坐监。至于以巴弗为何被捕，我们不得而知。",
      "title": "腓利门书 23 研修本注释：与腓利门一样，以巴弗是歌罗西人",
      "type": "commentary",
      "verses": [
        "Phlm.1.23"
      ]
    },
    {
      "body": "马、亚里达古、底马、路加，西4:10、14也提到这四个人。关于马可，见徒12:12：关于亚里达古，见徒19:29。几乎可以肯定，这个路加就是《路加福音》和《使徒行传》的作者（另见西4:14：提后4:11）。保罗被关押在凯撒利亚两年，后来又在罗马被囚两年。在这四年期间，路加都与他在一起。令人惋惜的是，后来底马贪爱世界，离开了保罗（提后4:10）。",
      "debugMeta": {
        "coverageRanges": [
          {
            "end": "Phlm.1.24",
            "start": "Phlm.1.24"
          }
        ],
        "page": 4,
        "primaryAnchor": "Phlm.1.24",
        "sourceLabel": "圣经研修本 57_腓利门书【codex-v3】"
      },
      "id": "study-bible-phlm-24-p004-n026",
      "primaryAnchor": "Phlm.1.24",
      "searchText": "腓利门书 24 研修本注释\n马、亚里达古、底马、路加，西4:10、14也提到这四个人。关于马可，见徒12:12：关于亚里达古，见徒19:29。几乎可以肯定，这个路加就是《路加福音》和《使徒行传》的作者（另见西4:14：提后4:11）。保罗被关押在凯撒利亚两年，后来又…\n马、亚里达古、底马、路加，西4:10、14也提到这四个人。关于马可，见徒12:12：关于亚里达古，见徒19:29。几乎可以肯定，这个路加就是《路加福音》和《使徒行传》的作者（另见西4:14：提后4:11）。保罗被关押在凯撒利亚两年，后来又在罗马被囚两年。在这四年期间，路加都与他在一起。令人惋惜的是，后来底马贪爱世界，离开了保罗（提后4:10）。\n24\n圣经研修本 57_腓利门书【codex-v3】",
      "source": "圣经研修本 57_腓利门书【codex-v3】",
      "summary": "马、亚里达古、底马、路加，西4:10、14也提到这四个人。关于马可，见徒12:12：关于亚里达古，见徒19:29。几乎可以肯定，这个路加就是《路加福音》和《使徒行传》的作者（另见西4:14：提后4:11）。保罗被关押在凯撒利亚两年，后来又…",
      "title": "腓利门书 24 研修本注释",
      "type": "commentary",
      "verses": [
        "Phlm.1.24"
      ]
    },
    {
      "body": "本书信的第1节清楚指明，作者是保罗和提摩太。然而，从第4节开始直到结尾，作者都采用第一人称单数（\"我\"）来指代作者本人，显然使徒保罗才是这封信的主要作者。本书信的传统标题（\"保罗写给腓利门的信\"）表明，这是一封写给腓利门的信（或私函），作者保罗却希望本书信能念给在腓利门家里聚会的全体会众听（2节）。",
      "debugMeta": {
        "coverageRanges": [
          {
            "end": "Phlm.1.1",
            "start": "Phlm.1.1"
          }
        ],
        "page": 1,
        "primaryAnchor": "Phlm.1.1",
        "sourceLabel": "圣经研修本 57_腓利门书【codex-v3】"
      },
      "id": "study-bible-phlm-intro-p001-n001",
      "primaryAnchor": "Phlm.1.1",
      "searchText": "腓利门书 导论：作者和书名\n本书信的第1节清楚指明，作者是保罗和提摩太。然而，从第4节开始直到结尾，作者都采用第一人称单数（\"我\"）来指代作者本人，显然使徒保罗才是这封信的主要作者。本书信的传统标题（\"保罗写给腓利门的信\"）表明，这是一封写给腓利门的信（或私函），作…\n本书信的第1节清楚指明，作者是保罗和提摩太。然而，从第4节开始直到结尾，作者都采用第一人称单数（\"我\"）来指代作者本人，显然使徒保罗才是这封信的主要作者。本书信的传统标题（\"保罗写给腓利门的信\"）表明，这是一封写给腓利门的信（或私函），作者保罗却希望本书信能念给在腓利门家里聚会的全体会众听（2节）。\n导论：作者和书名\n圣经研修本 57_腓利门书【codex-v3】",
      "source": "圣经研修本 57_腓利门书【codex-v3】",
      "summary": "本书信的第1节清楚指明，作者是保罗和提摩太。然而，从第4节开始直到结尾，作者都采用第一人称单数（\"我\"）来指代作者本人，显然使徒保罗才是这封信的主要作者。本书信的传统标题（\"保罗写给腓利门的信\"）表明，这是一封写给腓利门的信（或私函），作…",
      "title": "腓利门书 导论：作者和书名",
      "type": "commentary",
      "verses": [
        "Phlm.1.1"
      ]
    },
    {
      "body": "这封信大概写于主后62年左右，写作时间与《歌罗西书》和《以弗所书》大致相近。这三封信都是由推基古和阿尼西母送递的。本书信的写作时间显示，保罗提到的被囚（见1、9、10、13、23节）地点是在罗马（徒27-28章）。",
      "debugMeta": {
        "coverageRanges": [
          {
            "end": "Phlm.1.9",
            "start": "Phlm.1.9"
          }
        ],
        "page": 1,
        "primaryAnchor": "Phlm.1.9",
        "sourceLabel": "圣经研修本 57_腓利门书【codex-v3】"
      },
      "id": "study-bible-phlm-intro-p001-n002",
      "primaryAnchor": "Phlm.1.9",
      "searchText": "腓利门书 导论：写作时间\n这封信大概写于主后62年左右，写作时间与《歌罗西书》和《以弗所书》大致相近。这三封信都是由推基古和阿尼西母送递的。本书信的写作时间显示，保罗提到的被囚（见1、9、10、13、23节）地点是在罗马（徒27-28章）。\n这封信大概写于主后62年左右，写作时间与《歌罗西书》和《以弗所书》大致相近。这三封信都是由推基古和阿尼西母送递的。本书信的写作时间显示，保罗提到的被囚（见1、9、10、13、23节）地点是在罗马（徒27-28章）。\n导论：写作时间\n圣经研修本 57_腓利门书【codex-v3】",
      "source": "圣经研修本 57_腓利门书【codex-v3】",
      "summary": "这封信大概写于主后62年左右，写作时间与《歌罗西书》和《以弗所书》大致相近。这三封信都是由推基古和阿尼西母送递的。本书信的写作时间显示，保罗提到的被囚（见1、9、10、13、23节）地点是在罗马（徒27-28章）。",
      "title": "腓利门书 导论：写作时间",
      "type": "commentary",
      "verses": [
        "Phlm.1.9"
      ]
    },
    {
      "body": "《腓利门书》的主题是：福音不仅有改变人生命的能力（11节\"他从前与你没有益处，但如今与你我都有益处\"），也有影响人际关系的能力（16节\"不再是奴仆，乃是高过奴仆，是亲爱的兄弟\"）。关于希腊原文doulos一词的解释，见《读者指南》。",
      "debugMeta": {
        "coverageRanges": [
          {
            "end": "Phlm.1.16",
            "start": "Phlm.1.16"
          }
        ],
        "page": 1,
        "primaryAnchor": "Phlm.1.16",
        "sourceLabel": "圣经研修本 57_腓利门书【codex-v3】"
      },
      "id": "study-bible-phlm-intro-p001-n003",
      "primaryAnchor": "Phlm.1.16",
      "searchText": "腓利门书 导论：主题\n《腓利门书》的主题是：福音不仅有改变人生命的能力（11节\"他从前与你没有益处，但如今与你我都有益处\"），也有影响人际关系的能力（16节\"不再是奴仆，乃是高过奴仆，是亲爱的兄弟\"）。关于希腊原文doulos一词的解释，见《读者指南》。\n《腓利门书》的主题是：福音不仅有改变人生命的能力（11节\"他从前与你没有益处，但如今与你我都有益处\"），也有影响人际关系的能力（16节\"不再是奴仆，乃是高过奴仆，是亲爱的兄弟\"）。关于希腊原文doulos一词的解释，见《读者指南》。\n导论：主题\n圣经研修本 57_腓利门书【codex-v3】",
      "source": "圣经研修本 57_腓利门书【codex-v3】",
      "summary": "《腓利门书》的主题是：福音不仅有改变人生命的能力（11节\"他从前与你没有益处，但如今与你我都有益处\"），也有影响人际关系的能力（16节\"不再是奴仆，乃是高过奴仆，是亲爱的兄弟\"）。关于希腊原文doulos一词的解释，见《读者指南》。",
      "title": "腓利门书 导论：主题",
      "type": "commentary",
      "verses": [
        "Phlm.1.16"
      ]
    },
    {
      "body": "腓利门是歌罗西城一位富有的基督徒。歌罗西是一座内陆城邑，距离以弗所大约161公里（见1928页地图）。保罗曾有三年时间在以弗所传道（主后52-55年），腓利门可能在那期间听到福音，蒙恩得救。随后，他开始在歌罗西侍奉基督，将自己的家开放给一群基督徒定期聚会。腓利门的奴仆阿尼西母逃到罗马去了。阿尼西母可能偷了腓利门的钱（或财物），离开主人的家，在罗马帝国人口最稠密的这个城市住下来，希望能不被发现。机缘巧合，阿尼西母认识了使徒保罗，并且成为基督徒。信中没有记载阿尼西母如何认识保罗，但当中必定有上帝的奇妙带领。保罗被囚禁后，行动严重受限。阿尼西母成为基督徒后，投入很多时间和精力来帮助保罗。保罗本想把阿尼西母留在身边，但他知道阿尼西母是逃奴，与主人的关系破裂，又做错了事得罪主人，所有这些问题都必须解决。于是保罗写了这封信，恳请腓利门欣赏阿尼西母属灵生命的改变，重新接纳他，不是只把他当作奴仆，而是看他为\"亲爱的兄弟\"（16节）保罗是否想使阿尼西母获得完全的解放，成为自由人，我们不得而知（见16节注，21节注）。但我们可以清楚看到的是，保罗努力寻求这奴仆和主人之间的关系得以改变。这种全新的关系会违反当时希腊罗马文化中那种根深蒂固的尊卑之别。无疑，有了保罗在信中营造的爱的氛围，从前那种奴役的状态应该很难维系下去。事实上，保罗在信中的诉求，已经为彻底废除这种奴隶制度奠定了基础。",
      "debugMeta": {
        "coverageRanges": [
          {
            "end": "Phlm.1.10",
            "start": "Phlm.1.10"
          }
        ],
        "page": 1,
        "primaryAnchor": "Phlm.1.10",
        "sourceLabel": "圣经研修本 57_腓利门书【codex-v3】"
      },
      "id": "study-bible-phlm-intro-p001-n004",
      "primaryAnchor": "Phlm.1.10",
      "searchText": "腓利门书 导论：写作目的、缘起和背景\n腓利门是歌罗西城一位富有的基督徒。歌罗西是一座内陆城邑，距离以弗所大约161公里（见1928页地图）。保罗曾有三年时间在以弗所传道（主后52-55年），腓利门可能在那期间听到福音，蒙恩得救。随后，他开始在歌罗西侍奉基督，将自己的家开放给一…\n腓利门是歌罗西城一位富有的基督徒。歌罗西是一座内陆城邑，距离以弗所大约161公里（见1928页地图）。保罗曾有三年时间在以弗所传道（主后52-55年），腓利门可能在那期间听到福音，蒙恩得救。随后，他开始在歌罗西侍奉基督，将自己的家开放给一群基督徒定期聚会。腓利门的奴仆阿尼西母逃到罗马去了。阿尼西母可能偷了腓利门的钱（或财物），离开主人的家，在罗马帝国人口最稠密的这个城市住下来，希望能不被发现。机缘巧合，阿尼西母认识了使徒保罗，并且成为基督徒。信中没有记载阿尼西母如何认识保罗，但当中必定有上帝的奇妙带领。保罗被囚禁后，行动严重受限。阿尼西母成为基督徒后，投入很多时间和精力来帮助保罗。保罗本想把阿尼西母留在身边，但他知道阿尼西母是逃奴，与主人的关系破裂，又做错了事得罪主人，所有这些问题都必须解决。于是保罗写了这封信，恳请腓利门欣赏阿尼西母属灵生命的改变，重新接纳他，不是只把他当作奴仆，而是看他为\"亲爱的兄弟\"（16节）保罗是否想使阿尼西母获得完全的解放，成为自由人，我们不得而知（见16节注，21节注）。但我们可以清楚看到的是，保罗努力寻求这奴仆和主人之间的关系得以改变。这种全新的关系会违反当时希腊罗马文化中那种根深蒂固的尊卑之别。无疑，有了保罗在信中营造的爱的氛围，从前那种奴役的状态应该很难维系下去。事实上，保罗在信中的诉求，已经为彻底废除这种奴隶制度奠定了基础。\n导论：写作目的、缘起和背景\n圣经研修本 57_腓利门书【codex-v3】",
      "source": "圣经研修本 57_腓利门书【codex-v3】",
      "summary": "腓利门是歌罗西城一位富有的基督徒。歌罗西是一座内陆城邑，距离以弗所大约161公里（见1928页地图）。保罗曾有三年时间在以弗所传道（主后52-55年），腓利门可能在那期间听到福音，蒙恩得救。随后，他开始在歌罗西侍奉基督，将自己的家开放给一…",
      "title": "腓利门书 导论：写作目的、缘起和背景",
      "type": "commentary",
      "verses": [
        "Phlm.1.10"
      ]
    },
    {
      "body": "耶稣基督受死和复活（主后33或30年）*保罗悔改归主（33/34年*）保罗第一次到访耶路撒冷（36/37年*）保罗第二次到访耶路撒冷（賑济饥荒灾民）（44-47年*）保罗第一次旅行传道（46-47年）保罗第三次到访耶路撒冷（使徒会议）（48-49年*）保罗第二次旅行传道（48/49-51年*）保罗第三次旅行传道（腓利门可能在以弗所悔改信主）（52-57年*）保罗在罗马被软禁，写信给腓利门（62年*）保罗在罗马殉道（64-67年*）*表示大致年份：/表示\"或\"：'见《圣经文集主后30 3540455055606570》中的《耶稣被钉十字架的年份》。",
      "debugMeta": {
        "coverageRanges": [
          {
            "end": "Phlm.1.9",
            "start": "Phlm.1.9"
          }
        ],
        "page": 2,
        "primaryAnchor": "Phlm.1.9",
        "sourceLabel": "圣经研修本 57_腓利门书【codex-v3】"
      },
      "id": "study-bible-phlm-intro-p002-n005",
      "primaryAnchor": "Phlm.1.9",
      "searchText": "腓利门书 导论：大事年表\n耶稣基督受死和复活（主后33或30年）*保罗悔改归主（33/34年*）保罗第一次到访耶路撒冷（36/37年*）保罗第二次到访耶路撒冷（賑济饥荒灾民）（44-47年*）保罗第一次旅行传道（46-47年）保罗第三次到访耶路撒冷（使徒会议）（4…\n耶稣基督受死和复活（主后33或30年）*保罗悔改归主（33/34年*）保罗第一次到访耶路撒冷（36/37年*）保罗第二次到访耶路撒冷（賑济饥荒灾民）（44-47年*）保罗第一次旅行传道（46-47年）保罗第三次到访耶路撒冷（使徒会议）（48-49年*）保罗第二次旅行传道（48/49-51年*）保罗第三次旅行传道（腓利门可能在以弗所悔改信主）（52-57年*）保罗在罗马被软禁，写信给腓利门（62年*）保罗在罗马殉道（64-67年*）*表示大致年份：/表示\"或\"：'见《圣经文集主后30 3540455055606570》中的《耶稣被钉十字架的年份》。\n导论：大事年表\n圣经研修本 57_腓利门书【codex-v3】",
      "source": "圣经研修本 57_腓利门书【codex-v3】",
      "summary": "耶稣基督受死和复活（主后33或30年）*保罗悔改归主（33/34年*）保罗第一次到访耶路撒冷（36/37年*）保罗第二次到访耶路撒冷（賑济饥荒灾民）（44-47年*）保罗第一次旅行传道（46-47年）保罗第三次到访耶路撒冷（使徒会议）（4…",
      "title": "腓利门书 导论：大事年表",
      "type": "commentary",
      "verses": [
        "Phlm.1.9"
      ]
    },
    {
      "body": "基督徒在基督里的彼此相待，必须因着基督的恩典而有所改变。关于\"救恩历史\"的解释，见《圣经文集》中的《〈圣经〉概述》。",
      "debugMeta": {
        "coverageRanges": [
          {
            "end": "Phlm.1.16",
            "start": "Phlm.1.16"
          }
        ],
        "page": 2,
        "primaryAnchor": "Phlm.1.16",
        "sourceLabel": "圣经研修本 57_腓利门书【codex-v3】"
      },
      "id": "study-bible-phlm-intro-p002-n006",
      "primaryAnchor": "Phlm.1.16",
      "searchText": "腓利门书 导论：救恩历史概要\n基督徒在基督里的彼此相待，必须因着基督的恩典而有所改变。关于\"救恩历史\"的解释，见《圣经文集》中的《〈圣经〉概述》。\n基督徒在基督里的彼此相待，必须因着基督的恩典而有所改变。关于\"救恩历史\"的解释，见《圣经文集》中的《〈圣经〉概述》。\n导论：救恩历史概要\n圣经研修本 57_腓利门书【codex-v3】",
      "source": "圣经研修本 57_腓利门书【codex-v3】",
      "summary": "基督徒在基督里的彼此相待，必须因着基督的恩典而有所改变。关于\"救恩历史\"的解释，见《圣经文集》中的《〈圣经〉概述》。",
      "title": "腓利门书 导论：救恩历史概要",
      "type": "commentary",
      "verses": [
        "Phlm.1.16"
      ]
    },
    {
      "body": "就文体格式而言，标准的新约书信通常有五个部分，而这封简短的书信却大不一样，像是一封日常信件。这封信堪称是劝说名篇，我们从中可以看出保罗怎样规劝主人乐意接纳一个回转的奴隶。在当时，主人通常是不会饶恕逃奴的。保罗的劝说策略遵循当时希腊人和罗马人的雄辩术：先与收信人建立友好的关系（4-10节），然后以能够说服收信人的方式陈明事实（11-19节），最后用感情来影响收信人的决定（20-21节）。",
      "debugMeta": {
        "coverageRanges": [
          {
            "end": "Phlm.1.8",
            "start": "Phlm.1.8"
          }
        ],
        "page": 2,
        "primaryAnchor": "Phlm.1.8",
        "sourceLabel": "圣经研修本 57_腓利门书【codex-v3】"
      },
      "id": "study-bible-phlm-intro-p002-n007",
      "primaryAnchor": "Phlm.1.8",
      "searchText": "腓利门书 导论：文学特征\n就文体格式而言，标准的新约书信通常有五个部分，而这封简短的书信却大不一样，像是一封日常信件。这封信堪称是劝说名篇，我们从中可以看出保罗怎样规劝主人乐意接纳一个回转的奴隶。在当时，主人通常是不会饶恕逃奴的。保罗的劝说策略遵循当时希腊人和罗马…\n就文体格式而言，标准的新约书信通常有五个部分，而这封简短的书信却大不一样，像是一封日常信件。这封信堪称是劝说名篇，我们从中可以看出保罗怎样规劝主人乐意接纳一个回转的奴隶。在当时，主人通常是不会饶恕逃奴的。保罗的劝说策略遵循当时希腊人和罗马人的雄辩术：先与收信人建立友好的关系（4-10节），然后以能够说服收信人的方式陈明事实（11-19节），最后用感情来影响收信人的决定（20-21节）。\n导论：文学特征\n圣经研修本 57_腓利门书【codex-v3】",
      "source": "圣经研修本 57_腓利门书【codex-v3】",
      "summary": "就文体格式而言，标准的新约书信通常有五个部分，而这封简短的书信却大不一样，像是一封日常信件。这封信堪称是劝说名篇，我们从中可以看出保罗怎样规劝主人乐意接纳一个回转的奴隶。在当时，主人通常是不会饶恕逃奴的。保罗的劝说策略遵循当时希腊人和罗马…",
      "title": "腓利门书 导论：文学特征",
      "type": "commentary",
      "verses": [
        "Phlm.1.8"
      ]
    },
    {
      "body": "1.和好是这封信的核心主题。阿尼西母已经与上2.保罗请求腓利门，是基于基督至高的爱，而不向那一地区的所有信徒显出爱心。帝和好了，如今他要与一位主内弟兄和好。是出于罗马的社会习俗。保罗称赞腓利门，因为腓利门不仅",
      "debugMeta": {
        "coverageRanges": [
          {
            "end": "Phlm.1.17",
            "start": "Phlm.1.17"
          }
        ],
        "page": 2,
        "primaryAnchor": "Phlm.1.17",
        "sourceLabel": "圣经研修本 57_腓利门书【codex-v3】"
      },
      "id": "study-bible-phlm-intro-p002-n008",
      "primaryAnchor": "Phlm.1.17",
      "searchText": "腓利门书 导论：关键主题\n1.和好是这封信的核心主题。阿尼西母已经与上2.保罗请求腓利门，是基于基督至高的爱，而不向那一地区的所有信徒显出爱心。帝和好了，如今他要与一位主内弟兄和好。是出于罗马的社会习俗。保罗称赞腓利门，因为腓利门不仅\n1.和好是这封信的核心主题。阿尼西母已经与上2.保罗请求腓利门，是基于基督至高的爱，而不向那一地区的所有信徒显出爱心。帝和好了，如今他要与一位主内弟兄和好。是出于罗马的社会习俗。保罗称赞腓利门，因为腓利门不仅\n导论：关键主题\n圣经研修本 57_腓利门书【codex-v3】",
      "source": "圣经研修本 57_腓利门书【codex-v3】",
      "summary": "1.和好是这封信的核心主题。阿尼西母已经与上2.保罗请求腓利门，是基于基督至高的爱，而不向那一地区的所有信徒显出爱心。帝和好了，如今他要与一位主内弟兄和好。是出于罗马的社会习俗。保罗称赞腓利门，因为腓利门不仅",
      "title": "腓利门书 导论：关键主题",
      "type": "commentary",
      "verses": [
        "Phlm.1.17"
      ]
    },
    {
      "body": "一、问候（1-3节）二、感恩和祷告（4-7节）三、保罗为阿尼西母向腓利门求情（8-20节）四、结语和问候（21-25节）",
      "debugMeta": {
        "coverageRanges": [
          {
            "end": "Phlm.1.8",
            "start": "Phlm.1.8"
          }
        ],
        "page": 2,
        "primaryAnchor": "Phlm.1.8",
        "sourceLabel": "圣经研修本 57_腓利门书【codex-v3】"
      },
      "id": "study-bible-phlm-intro-p002-n009",
      "primaryAnchor": "Phlm.1.8",
      "searchText": "腓利门书 导论：大纲\n一、问候（1-3节）二、感恩和祷告（4-7节）三、保罗为阿尼西母向腓利门求情（8-20节）四、结语和问候（21-25节）\n一、问候（1-3节）二、感恩和祷告（4-7节）三、保罗为阿尼西母向腓利门求情（8-20节）四、结语和问候（21-25节）\n导论：大纲\n圣经研修本 57_腓利门书【codex-v3】",
      "source": "圣经研修本 57_腓利门书【codex-v3】",
      "summary": "一、问候（1-3节）二、感恩和祷告（4-7节）三、保罗为阿尼西母向腓利门求情（8-20节）四、结语和问候（21-25节）",
      "title": "腓利门书 导论：大纲",
      "type": "commentary",
      "verses": [
        "Phlm.1.8"
      ]
    }
  ]
}
